{"name":"k-web","tagline":"clustering/classification web visualzation","body":"nn-web\r\n======\r\n\r\n    Author: Alexander Weigl\r\n    Date: 2013-09-27\r\n    License: gpl-v3\r\n\r\n\r\n\r\n\r\n## Included libraries\r\n\r\n*rng.js* for generating uniformly random numbers, see https://github.com/skeeto/rng-js/\r\n\r\n*rhill-voronoi-core.min.js* for visualizing the cluster from the k-means clustering, see\r\nhttps://github.com/gorhill/Javascript-Voronoi (MIT License)\r\n","google":"","note":"Don't delete this file! It's used internally to help with page regeneration."}